owl_robot_sdk/__init__.py
owl_robot_sdk/client/__init__.py
owl_robot_sdk/client/robot.py
owl_robot_sdk-0.14.dist-info/METADATA
owl_robot_sdk-0.14.dist-info/WHEEL
owl_robot_sdk-0.14.dist-info/top_level.txt
owl_robot_sdk-0.14.dist-info/RECORD
