Metadata-Version: 2.1
Name: owl-robot-sdk
Version: 0.14
Summary: A python client library to operate OWL Robot in Gazebo and MoveIt.
Home-page: UNKNOWN
Author: Lentin Joseph
Author-email: lentin@orangewood.co
License: Orangewood Labs Inc. 
Platform: UNKNOWN
